juntagrico_custom_sub/__init__.py
juntagrico_custom_sub/admin.py
juntagrico_custom_sub/apps.py
juntagrico_custom_sub/basimilch.py
juntagrico_custom_sub/config.py
juntagrico_custom_sub/models.py
juntagrico_custom_sub/urls.py
juntagrico_custom_sub/views.py
juntagrico_custom_sub/downgrade/urls_1_5.py
juntagrico_custom_sub/downgrade/views_1_5.py
juntagrico_custom_sub/entity/__init__.py
juntagrico_custom_sub/entity/cs_depot.py
juntagrico_custom_sub/entity/custom_delivery.py
juntagrico_custom_sub/entity/product.py
juntagrico_custom_sub/entity/subscription_content.py
juntagrico_custom_sub/entity/subscription_content_future_item.py
juntagrico_custom_sub/entity/subscription_content_item.py
juntagrico_custom_sub/entity/subscription_size_mandatory_products.py
juntagrico_custom_sub/management/__init__.py
juntagrico_custom_sub/management/commands/__init__.py
juntagrico_custom_sub/management/commands/cs_generate_basic_data.py
juntagrico_custom_sub/management/commands/cs_generate_depot_list.py
juntagrico_custom_sub/management/commands/cs_generate_testdata.py
juntagrico_custom_sub/migrations/0001_initial.py
juntagrico_custom_sub/migrations/0002_auto_20190317_1604.py
juntagrico_custom_sub/migrations/0003_auto_20190815_2036.py
juntagrico_custom_sub/migrations/0004_auto_20191005_1144.py
juntagrico_custom_sub/migrations/0005_customdelivery_delivery_comment.py
juntagrico_custom_sub/migrations/0006_auto_20191113_2304.py
juntagrico_custom_sub/migrations/0007_csdepot.py
juntagrico_custom_sub/migrations/0008_auto_20191209_2003.py
juntagrico_custom_sub/migrations/0009_product_code.py
juntagrico_custom_sub/migrations/0010_generate_code.py
juntagrico_custom_sub/migrations/0011_enforce_constraints.py
juntagrico_custom_sub/migrations/0012_alter_subscriptioncontent_subscription.py
juntagrico_custom_sub/migrations/__init__.py
juntagrico_custom_sub/static/juntagrico_custom_sub/style.css
juntagrico_custom_sub/templates/createsubscription/summary.html
juntagrico_custom_sub-1.7.2.dist-info/licenses/LICENSE
juntagrico_custom_sub-1.7.2.dist-info/METADATA
juntagrico_custom_sub-1.7.2.dist-info/WHEEL
juntagrico_custom_sub-1.7.2.dist-info/top_level.txt
juntagrico_custom_sub-1.7.2.dist-info/RECORD
